Metadata-Version: 2.1
Name: Mensajes-silvai
Version: 7.0
Summary: Un paquete para saludar y despedir
Home-page: https://www.hektor.dev
Author: Isaac Silva
Author-email: ijsc_11@hotmail.com
Classifier: Environment :: Console
Classifier: Intended Audience :: Developers
Classifier: License :: OSI Approved :: MIT License
Classifier: Operating System :: OS Independent
Classifier: Programming Language :: Python
Classifier: Programming Language :: Python :: 3.9
Classifier: Programming Language :: Python :: 3.10
Classifier: Programming Language :: Python :: 3.11
Classifier: Topic :: Utilities
License-File: LICENSE
Requires-Dist: numpy (==1.23.5)
